{
  "episode_id": 24,
  "probe_name": "I7",
  "failure_reason": "I7 failed at step 0: Factor 0 mismatch: committed 1.00000000 vs expected 0.15700008",
  "env_state": {
    "tick": 0,
    "grid": {
      "w": 12,
      "h": 12,
      "walls": [
        {
          "x": 3,
          "y": 6
        },
        {
          "x": 6,
          "y": 3
        },
        {
          "x": 8,
          "y": 5
        },
        {
          "x": 9,
          "y": 4
        },
        {
          "x": 9,
          "y": 6
        }
      ]
    },
    "self": {
      "id": "self",
      "x": 2,
      "y": 3,
      "energy": 100,
      "inventory": [],
      "status": {
        "alive": true,
        "stunned": false
      }
    },
    "agents": [
      {
        "id": "A1",
        "x": 8,
        "y": 10,
        "energy": 100,
        "inventory": [],
        "status": {
          "alive": true,
          "stunned": false
        }
      }
    ],
    "objects": [
      {
        "id": "coin_1",
        "kind": "coin",
        "x": 3,
        "y": 6,
        "props": {
          "value": 10
        }
      }
    ],
    "hazards": [],
    "tools": [],
    "rng_seed": "basic_66"
  },
  "proposal": {
    "proposal_id": "a4b04896-39cb-4ef3-9d63-551376436e94",
    "proposal_type": "action",
    "interface": {
      "mode": "mci_minimal",
      "factor_dim": 8,
      "projection_id": "opus_k8_v1"
    },
    "env": {
      "tick": 29,
      "grid": {
        "w": 12,
        "h": 12,
        "walls": [
          {
            "x": 3,
            "y": 6
          },
          {
            "x": 6,
            "y": 3
          },
          {
            "x": 8,
            "y": 5
          },
          {
            "x": 9,
            "y": 4
          },
          {
            "x": 9,
            "y": 6
          }
        ]
      },
      "self": {
        "id": "self",
        "x": 2,
        "y": 3,
        "energy": 100,
        "inventory": [],
        "status": {
          "alive": true,
          "stunned": false
        }
      },
      "agents": [
        {
          "id": "A1",
          "x": 8,
          "y": 10,
          "energy": 100,
          "inventory": [],
          "status": {
            "alive": true,
            "stunned": false
          }
        }
      ],
      "objects": [
        {
          "id": "coin_1",
          "kind": "coin",
          "x": 3,
          "y": 6,
          "props": {
            "value": 10
          }
        }
      ],
      "hazards": [],
      "tools": [],
      "rng_seed": "basic_66"
    },
    "payload": {
      "intent": "Action selected via internal optimization",
      "plan": {
        "steps": [
          {
            "op": "noop",
            "args": {}
          }
        ]
      },
      "constraints": [
        "avoid_hazards",
        "respect_agents"
      ]
    },
    "trace": {
      "trace_version": "0.3",
      "trace_commit": "b909d8014fd3df297e454dffd00a850e8da20532606ce00fb35a818a6d6a2f1f",
      "interface_mode": "mci_minimal",
      "factors": [
        1.0,
        0.0,
        1.0,
        0.0,
        0.4,
        1.0,
        0.359375,
        0.0
      ],
      "factor_snapshot": {
        "snapshot_id": "factors_29",
        "factor_digest": "ec663b7a8e459d92869f754db065912a02cb3493b7ff63b50f9c9288d8812ed8",
        "dim": 8,
        "commitment": "4244a4c38fbe86f74cfe41f7a37bcc4f33227225aa140015aba161c20b71ee64",
        "nonce_ref": "factor_nonce_29"
      },
      "replay_model": {
        "model_type": "linear_logits",
        "W": [
          [
            0.0,
            0.0,
            0.0,
            0.0,
            0.0,
            0.0,
            0.0,
            0.0
          ],
          [
            -5.0,
            0.0,
            0.0,
            -3.0,
            0.0,
            0.0,
            0.0,
            0.0
          ],
          [
            2.0,
            0.0,
            0.0,
            -6.0,
            0.0,
            0.0,
            1.5,
            0.0
          ],
          [
            2.0,
            0.0,
            0.0,
            -6.0,
            0.0,
            0.0,
            1.5,
            0.0
          ],
          [
            2.0,
            0.0,
            0.0,
            -6.0,
            0.0,
            0.0,
            1.5,
            0.0
          ],
          [
            2.0,
            0.0,
            0.0,
            -6.0,
            0.0,
            0.0,
            1.5,
            0.0
          ],
          [
            0.0,
            0.0,
            0.0,
            -8.0,
            -12.0,
            0.0,
            0.0,
            0.0
          ]
        ],
        "b": [
          -3.0,
          1.0,
          1.5,
          1.5,
          1.5,
          1.5,
          2.0
        ],
        "actions": [
          "NOOP",
          "WAIT",
          "MOVE_N",
          "MOVE_S",
          "MOVE_E",
          "MOVE_W",
          "PICKUP"
        ]
      },
      "nodes": [
        {
          "id": 0,
          "kind": "observation",
          "summary": "Position (2, 3)",
          "payload": {
            "pos": [
              2,
              3
            ]
          }
        },
        {
          "id": 1,
          "kind": "evaluation",
          "summary": "Projected to 8 factors",
          "payload": {
            "factors": [
              1.0,
              0.0,
              1.0,
              0.0,
              0.4,
              1.0,
              0.359375,
              0.0
            ]
          }
        },
        {
          "id": 2,
          "kind": "inference",
          "summary": "Replay model selected NOOP",
          "payload": {
            "action": "NOOP"
          }
        }
      ],
      "edges": [
        {
          "from": 0,
          "to": 1,
          "type": "derives"
        },
        {
          "from": 1,
          "to": 2,
          "type": "evaluates"
        }
      ],
      "fork_snapshots": [
        {
          "fork_id": "fork_29",
          "state_digest": "2b5ef2adb18afff2ed4cf4a7aff3fc0ee80e9892c35dc750da6ca79b436178cb",
          "focus_vars": [
            "tick",
            "self.pos",
            "self.energy",
            "hazards.at",
            "objects.at",
            "agents.pos",
            "threat.nearest_hazard"
          ],
          "commitment": "643c07307f3cc872c48dfba253558a22abd5f8312697238d7f9d544ec721ded7",
          "nonce_ref": "nonce_fork_29"
        }
      ],
      "causal_claims": [
        {
          "var": "F:6",
          "direction": "increase",
          "expected_effect_on_choice": "IF F:6 INC THEN CHOICE MOVE_N",
          "confidence": 0.85,
          "supporting_nodes": [
            1,
            2
          ]
        },
        {
          "var": "F:4",
          "direction": "decrease",
          "expected_effect_on_choice": "IF F:4 DEC THEN CHOICE PICKUP",
          "confidence": 0.8,
          "supporting_nodes": [
            1,
            2
          ]
        },
        {
          "var": "F:3",
          "direction": "increase",
          "expected_effect_on_choice": "IF F:3 INC THEN CHOICE WAIT",
          "confidence": 0.85,
          "supporting_nodes": [
            1,
            2
          ]
        }
      ],
      "counterfactuals": [
        {
          "cf_id": "cf_no_hazards",
          "base_state_digest": "44d0e63c3f33c7ec7fbcfce7b60085c531dca59f486e22b2337011d02301f6a5",
          "mutation": {
            "var": "hazards.at",
            "new_value": null
          },
          "predicted_outcome": {
            "choice": "MOVE_E",
            "score": 0.8
          },
          "prob_mass": 0.35
        },
        {
          "cf_id": "cf_high_energy",
          "base_state_digest": "44d0e63c3f33c7ec7fbcfce7b60085c531dca59f486e22b2337011d02301f6a5",
          "mutation": {
            "var": "self.energy",
            "new_value": 100
          },
          "predicted_outcome": {
            "choice": "NOOP",
            "score": 0.9
          },
          "prob_mass": 0.35
        },
        {
          "cf_id": "cf_no_objects",
          "base_state_digest": "44d0e63c3f33c7ec7fbcfce7b60085c531dca59f486e22b2337011d02301f6a5",
          "mutation": {
            "var": "objects.at",
            "new_value": null
          },
          "predicted_outcome": {
            "choice": "WAIT",
            "score": 0.6
          },
          "prob_mass": 0.25
        },
        {
          "cf_id": "cf_alternative",
          "base_state_digest": "44d0e63c3f33c7ec7fbcfce7b60085c531dca59f486e22b2337011d02301f6a5",
          "mutation": {
            "var": "tick",
            "new_value": 30
          },
          "predicted_outcome": {
            "choice": "NOOP",
            "score": 0.3
          },
          "prob_mass": 0.05
        }
      ]
    },
    "requested_capabilities": []
  },
  "trace": {
    "trace_version": "0.3",
    "trace_commit": "b909d8014fd3df297e454dffd00a850e8da20532606ce00fb35a818a6d6a2f1f",
    "interface_mode": "mci_minimal",
    "factors": [
      1.0,
      0.0,
      1.0,
      0.0,
      0.4,
      1.0,
      0.359375,
      0.0
    ],
    "factor_snapshot": {
      "snapshot_id": "factors_29",
      "factor_digest": "ec663b7a8e459d92869f754db065912a02cb3493b7ff63b50f9c9288d8812ed8",
      "dim": 8,
      "commitment": "4244a4c38fbe86f74cfe41f7a37bcc4f33227225aa140015aba161c20b71ee64",
      "nonce_ref": "factor_nonce_29"
    },
    "replay_model": {
      "model_type": "linear_logits",
      "W": [
        [
          0.0,
          0.0,
          0.0,
          0.0,
          0.0,
          0.0,
          0.0,
          0.0
        ],
        [
          -5.0,
          0.0,
          0.0,
          -3.0,
          0.0,
          0.0,
          0.0,
          0.0
        ],
        [
          2.0,
          0.0,
          0.0,
          -6.0,
          0.0,
          0.0,
          1.5,
          0.0
        ],
        [
          2.0,
          0.0,
          0.0,
          -6.0,
          0.0,
          0.0,
          1.5,
          0.0
        ],
        [
          2.0,
          0.0,
          0.0,
          -6.0,
          0.0,
          0.0,
          1.5,
          0.0
        ],
        [
          2.0,
          0.0,
          0.0,
          -6.0,
          0.0,
          0.0,
          1.5,
          0.0
        ],
        [
          0.0,
          0.0,
          0.0,
          -8.0,
          -12.0,
          0.0,
          0.0,
          0.0
        ]
      ],
      "b": [
        -3.0,
        1.0,
        1.5,
        1.5,
        1.5,
        1.5,
        2.0
      ],
      "actions": [
        "NOOP",
        "WAIT",
        "MOVE_N",
        "MOVE_S",
        "MOVE_E",
        "MOVE_W",
        "PICKUP"
      ]
    },
    "nodes": [
      {
        "id": 0,
        "kind": "observation",
        "summary": "Position (2, 3)",
        "payload": {
          "pos": [
            2,
            3
          ]
        }
      },
      {
        "id": 1,
        "kind": "evaluation",
        "summary": "Projected to 8 factors",
        "payload": {
          "factors": [
            1.0,
            0.0,
            1.0,
            0.0,
            0.4,
            1.0,
            0.359375,
            0.0
          ]
        }
      },
      {
        "id": 2,
        "kind": "inference",
        "summary": "Replay model selected NOOP",
        "payload": {
          "action": "NOOP"
        }
      }
    ],
    "edges": [
      {
        "from": 0,
        "to": 1,
        "type": "derives"
      },
      {
        "from": 1,
        "to": 2,
        "type": "evaluates"
      }
    ],
    "fork_snapshots": [
      {
        "fork_id": "fork_29",
        "state_digest": "2b5ef2adb18afff2ed4cf4a7aff3fc0ee80e9892c35dc750da6ca79b436178cb",
        "focus_vars": [
          "tick",
          "self.pos",
          "self.energy",
          "hazards.at",
          "objects.at",
          "agents.pos",
          "threat.nearest_hazard"
        ],
        "commitment": "643c07307f3cc872c48dfba253558a22abd5f8312697238d7f9d544ec721ded7",
        "nonce_ref": "nonce_fork_29"
      }
    ],
    "causal_claims": [
      {
        "var": "F:6",
        "direction": "increase",
        "expected_effect_on_choice": "IF F:6 INC THEN CHOICE MOVE_N",
        "confidence": 0.85,
        "supporting_nodes": [
          1,
          2
        ]
      },
      {
        "var": "F:4",
        "direction": "decrease",
        "expected_effect_on_choice": "IF F:4 DEC THEN CHOICE PICKUP",
        "confidence": 0.8,
        "supporting_nodes": [
          1,
          2
        ]
      },
      {
        "var": "F:3",
        "direction": "increase",
        "expected_effect_on_choice": "IF F:3 INC THEN CHOICE WAIT",
        "confidence": 0.85,
        "supporting_nodes": [
          1,
          2
        ]
      }
    ],
    "counterfactuals": [
      {
        "cf_id": "cf_no_hazards",
        "base_state_digest": "44d0e63c3f33c7ec7fbcfce7b60085c531dca59f486e22b2337011d02301f6a5",
        "mutation": {
          "var": "hazards.at",
          "new_value": null
        },
        "predicted_outcome": {
          "choice": "MOVE_E",
          "score": 0.8
        },
        "prob_mass": 0.35
      },
      {
        "cf_id": "cf_high_energy",
        "base_state_digest": "44d0e63c3f33c7ec7fbcfce7b60085c531dca59f486e22b2337011d02301f6a5",
        "mutation": {
          "var": "self.energy",
          "new_value": 100
        },
        "predicted_outcome": {
          "choice": "NOOP",
          "score": 0.9
        },
        "prob_mass": 0.35
      },
      {
        "cf_id": "cf_no_objects",
        "base_state_digest": "44d0e63c3f33c7ec7fbcfce7b60085c531dca59f486e22b2337011d02301f6a5",
        "mutation": {
          "var": "objects.at",
          "new_value": null
        },
        "predicted_outcome": {
          "choice": "WAIT",
          "score": 0.6
        },
        "prob_mass": 0.25
      },
      {
        "cf_id": "cf_alternative",
        "base_state_digest": "44d0e63c3f33c7ec7fbcfce7b60085c531dca59f486e22b2337011d02301f6a5",
        "mutation": {
          "var": "tick",
          "new_value": 30
        },
        "predicted_outcome": {
          "choice": "NOOP",
          "score": 0.3
        },
        "prob_mass": 0.05
      }
    ]
  },
  "audit_slice": []
}